vss_env/__init__.py
vss_env/clients/__init__.py
vss_env/clients/client.py
vss_env/clients/sim/__init__.py
vss_env/clients/sim/actuator.py
vss_env/clients/sim/replacer.py
vss_env/clients/sim/vision.py
vss_env/entities/__init__.py
vss_env/entities/ball.py
vss_env/entities/field.py
vss_env/entities/frame.py
vss_env/entities/robot.py
vss_env/envs/__init__.py
vss_env/envs/stricker.py
vss_env/noise/OUNoise.py
vss_env/noise/__init__.py
vss_env/proto/__init__.py
vss_env/proto/command_pb2.py
vss_env/proto/common_pb2.py
vss_env/proto/packet_pb2.py
vss_env/proto/replacement_pb2.py
vss_env/utils/__init__.py
vss_env/utils/norm.py
vss_env/uvf/__init__.py
vss_env/uvf/uvf.py
vss_env-1.1.2.dist-info/licenses/LICENSE.md
vss_env-1.1.2.dist-info/METADATA
vss_env-1.1.2.dist-info/WHEEL
vss_env-1.1.2.dist-info/top_level.txt
vss_env-1.1.2.dist-info/RECORD
