Metadata-Version: 2.4
Name: vss-env
Version: 1.1.2
Summary: Framework para desenvolvimento de técnicas de Reinforcement Learning para futebol de robos.
Author-email: Davi Rosim <davi.rosim@ges.inatel.br>
License: MIT License
Classifier: Programming Language :: Python :: 3
Classifier: Operating System :: OS Independent
Classifier: License :: OSI Approved :: MIT License
Classifier: Intended Audience :: Science/Research
Classifier: Topic :: Scientific/Engineering :: Artificial Intelligence
Requires-Python: <3.11,>=3.10
License-File: LICENSE.md
Requires-Dist: cloudpickle==3.1.0
Requires-Dist: Farama-Notifications==0.0.4
Requires-Dist: grpcio==1.69.0
Requires-Dist: gymnasium==1.0.0
Requires-Dist: importlib-metadata==8.5.0
Requires-Dist: numpy~=2.2.3
Requires-Dist: protobuf==3.20.3
Requires-Dist: six==1.17.0
Requires-Dist: typing-extensions==4.12.2
Requires-Dist: zipp==3.21.0
Provides-Extra: dev
Requires-Dist: pytest~=8.3.5; extra == "dev"
Dynamic: license-file
